pytest_pudb.py
pytest_pudb-0.7.0.dist-info/LICENSE
pytest_pudb-0.7.0.dist-info/METADATA
pytest_pudb-0.7.0.dist-info/WHEEL
pytest_pudb-0.7.0.dist-info/entry_points.txt
pytest_pudb-0.7.0.dist-info/top_level.txt
pytest_pudb-0.7.0.dist-info/RECORD
