Metadata-Version: 2.1
Name: pytest-pudb
Version: 0.7.0
Summary: Pytest PuDB debugger integration
Home-page: https://github.com/wronglink/pytest-pudb
Author: Michael Elovskikh
Author-email: wronglink@gmail.com
License: MIT
Platform: UNKNOWN
Classifier: Development Status :: 3 - Alpha
Classifier: Topic :: Software Development :: Testing
Classifier: Intended Audience :: Developers
Classifier: Operating System :: OS Independent
Requires-Dist: pytest (>=2.0)
Requires-Dist: pudb
Provides-Extra: dev
Requires-Dist: pexpect; extra == 'dev'
Requires-Dist: tox; extra == 'dev'
Requires-Dist: flake8; extra == 'dev'
